{
    "project_name": "",
    "github_username": "IgnisDa",
    "github_name": "Diptesh Choudhuri",
    "github_email": "ignisda2001@gmail.com",
    "django_project_name": "backend",
    "django_user_model_app": "accounts",
    "nuxt_project_name": "frontend",
    "docs_project_name": "docs",
    "postgres_admin_user": "admin-user",
    "postgres_password": "admin-password",
    "postgres_database_name": "website-db",
    "_copy_without_render": [
        "**/index.js",
        "**/node_modules/*",
        "**/docs/*.md"
    ],
    "_extensions": [
        "cookiecutter.extensions.RandomStringExtension"
    ]
}
